streamlit_counterfactual_slider/__init__.py
streamlit_counterfactual_slider/frontend/build/asset-manifest.json
streamlit_counterfactual_slider/frontend/build/bootstrap.min.css
streamlit_counterfactual_slider/frontend/build/index.html
streamlit_counterfactual_slider/frontend/build/static/js/main.0156be7b.js
streamlit_counterfactual_slider/frontend/build/static/js/main.0156be7b.js.LICENSE.txt
streamlit_counterfactual_slider/frontend/build/static/js/main.0156be7b.js.map
streamlit_counterfactual_slider/frontend/build/static/js/main.50137df6.js
streamlit_counterfactual_slider/frontend/build/static/js/main.50137df6.js.LICENSE.txt
streamlit_counterfactual_slider/frontend/build/static/js/main.50137df6.js.map
streamlit_counterfactual_slider/frontend/build/static/js/main.bab39aaa.js
streamlit_counterfactual_slider/frontend/build/static/js/main.bab39aaa.js.LICENSE.txt
streamlit_counterfactual_slider/frontend/build/static/js/main.bab39aaa.js.map
streamlit_counterfactual_slider/frontend/build/static/js/main.be26772e.js
streamlit_counterfactual_slider/frontend/build/static/js/main.be26772e.js.LICENSE.txt
streamlit_counterfactual_slider/frontend/build/static/js/main.be26772e.js.map
streamlit_counterfactual_slider-0.3.0.dist-info/licenses/LICENSE
streamlit_counterfactual_slider-0.3.0.dist-info/METADATA
streamlit_counterfactual_slider-0.3.0.dist-info/WHEEL
streamlit_counterfactual_slider-0.3.0.dist-info/top_level.txt
streamlit_counterfactual_slider-0.3.0.dist-info/RECORD
